findCPcore/AbstractMetabolicModel.py
findCPcore/CobraMetabolicModel.py
findCPcore/Facade.py
findCPcore/FacadeThread.py
findCPcore/FacadeUtils.py
findCPcore/MetabolicModel.py
findCPcore/Spreadsheet.py
findCPcore/State.py
findCPcore/__init__.py
findCPcore/util.py
findCPcore/utils/CustomLogger.py
findCPcore/utils/GrowthDependentCPConfig.py
findCPcore/utils/__init__.py
findCPcore-0.1.1.dist-info/LICENSE
findCPcore-0.1.1.dist-info/METADATA
findCPcore-0.1.1.dist-info/WHEEL
findCPcore-0.1.1.dist-info/top_level.txt
findCPcore-0.1.1.dist-info/RECORD
