Metadata-Version: 2.1
Name: findCPcore
Version: 0.1.1
Summary: findCP core package
Home-page: https://github.com/findCP/findCPcore
Author: Alex Oarga
Author-email: alex718123@gmail.com
License: UNKNOWN
Platform: UNKNOWN
Classifier: Programming Language :: Python :: 3
Classifier: License :: OSI Approved :: GNU General Public License v3 or later (GPLv3+)
Classifier: Operating System :: OS Independent
Requires-Python: >=3.5
Requires-Dist: cobra (==0.16.0)
Requires-Dist: depinfo
Requires-Dist: python-dotenv
Requires-Dist: future
Requires-Dist: Jinja2
Requires-Dist: mpmath
Requires-Dist: numpy (>=1.16.5)
Requires-Dist: optlang (>=1.4.2)
Requires-Dist: pandas (>=0.17.0)
Requires-Dist: python-dateutil
Requires-Dist: python-libsbml
Requires-Dist: python-libsbml-experimental (==5.18.0)
Requires-Dist: pytz
Requires-Dist: ruamel.yaml (>=0.15)
Requires-Dist: setuptools
Requires-Dist: six
Requires-Dist: swiglpk
Requires-Dist: sympy
Requires-Dist: tabulate
Requires-Dist: xlwt (==1.3.0)
